{
  "name": "teams-sdk",
  "version": "1.4.0",
  "description": "Build, configure, and validate Microsoft Teams apps with the Teams Developer CLI. Includes the teams-dev skill (bot application development, infrastructure setup, SSO, troubleshooting) and the ngc-readiness skill (audit an app for New Gen Channels — shared & private channels — readiness).",
  "author": {
    "name": "Microsoft"
  },
  "homepage": "https://github.com/microsoft/teams-sdk",
  "license": "MIT",
  "skills": [
    "skills/teams-dev/",
    "skills/ngc-readiness/"
  ]
}
